{
	"app": {
		"bundleName": "com.tencent.tmm.ohoslib",
		"debug": false,
		"versionCode": 1000000,
		"versionName": "1.0.0",
		"minAPIVersion": 50000012,
		"targetAPIVersion": 50003015,
		"apiReleaseType": "Release",
		"compileSdkVersion": "5.0.3.135",
		"compileSdkType": "HarmonyOS",
		"appEnvironments": [],
		"bundleType": "app",
		"buildMode": "release"
	},
	"module": {
		"name": "knoi",
		"type": "har",
		"deviceTypes": [
			"default",
			"tablet",
			"2in1"
		],
		"packageName": "@kuiklybase/knoi",
		"installationFree": false,
		"virtualMachine": "ark12.0.2.0",
		"compileMode": "esmodule",
		"dependencies": []
	}
}
